{
    "title" : "My portfolio",
    "layoutButtons" : [
        "Projects",
        "About me"
    ],
    "primaryContentTitle": "My Projects",
    "searchbarText": "Search",
    "aboutMePanelTitle": "About Me",
    "personalInfoTitle": "Personal Info",
    "academicFormationTitle": "Academic Formation",
    "technicalSkillsTitle": "Technical Skills",
    "personalSkillsTitle": "Personal Skills",
    "aboutMeSection": "I'm a enthusiast about every technology related topic. Self improvement and discipline leads my values. I appreciate results over methods.",
    "personalInformationSection": [
        "Name: Lucas Nahuel Muñoz", "Location: Argentina, Chaco, Resistencia", "Mobile Number: +54 9 3625 253073", "Email: munozlucas96@gmail.com"
    ],
    "academicFormation": "Universitary Programming Technician, Universidad Tecnológica Nacional, August 2019 (concluded)",
    "technicalSkills": [
        "Frameworks/Languajes/Platforms i've worked with: HTML, CSS, Angular (typeScript, material), Java (Spring Boot, JPA), SQL ( MSSQL, MySQL ), .NET (C#, MVC), Node.js (JavaScript, Express), MongoDB (NoSQL), GitHub (GIT CLI). ",
        "Idioms: Spanish, English."
    ],
    "personalSkills": [
        "honesty", "responsability", "punctuality", "objectivity", "pragmatism"
    ]
}